{"queryCost":1,"latitude":13.4689,"longitude":121.857,"resolvedAddress":"Anapog-Sibucao, Mogpog, Mimaropa, Philippines","address":"Anapog-Sibucao,+Mogpog,+Marinduque","timezone":"Asia\/Manila","tzoffset":8,"description":"Similar temperatures continuing with no rain expected.","days":[{"datetime":"2026-03-11","datetimeEpoch":1773158400,"tempmax":26.6,"tempmin":24.5,"temp":25.4,"feelslikemax":26.6,"feelslikemin":24.5,"feelslike":25.4,"dew":19.5,"humidity":69.8,"precip":0.2,"precipprob":100,"precipcover":8.33,"preciptype":["rain"],"snow":0,"snowdepth":null,"windgust":40.7,"windspeed":38.5,"winddir":36.7,"pressure":1012.5,"cloudcover":30.6,"visibility":24.1,"solarradiation":302.8,"solarenergy":26.2,"uvindex":10,"severerisk":10,"sunrise":"06:02:56","sunriseEpoch":1773180176,"sunset":"18:02:40","sunsetEpoch":1773223360,"moonphase":0.75,"conditions":"Rain, Partially cloudy","description":"Becoming cloudy in the afternoon with early morning rain.","icon":"rain","stations":["remote"],"source":"comb","hours":[{"datetime":"00:00:00","datetimeEpoch":1773158400,"temp":24.6,"feelslike":24.6,"humidity":71.91,"dew":19.2,"precip":0,"precipprob":0,"snow":0,"snowdepth":null,"preciptype":null,"windgust":36.4,"windspeed":29.2,"winddir":50.2,"pressure":1015,"visibility":24.1,"cloudcover":100,"solarradiation":0,"solarenergy":0,"uvindex":0,"severerisk":10,"conditions":"Overcast","icon":"cloudy","stations":["remote"],"source":"obs"},{"datetime":"01:00:00","datetimeEpoch":1773162000,"temp":24.6,"feelslike":24.6,"humidity":72.82,"dew":19.4,"precip":0.1,"precipprob":100,"snow":0,"snowdepth":null,"preciptype":["rain"],"windgust":37.1,"windspeed":30.6,"winddir":48.7,"pressure":1014,"visibility":24.1,"cloudcover":4.4,"solarradiation":0,"solarenergy":0,"uvindex":0,"severerisk":10,"conditions":"Rain","icon":"rain","stations":["remote"],"source":"obs"},{"datetime":"02:00:00","datetimeEpoch":1773165600,"temp":24.6,"feelslike":24.6,"humidity":72.82,"dew":19.4,"precip":0,"precipprob":0,"snow":null,"snowdepth":null,"preciptype":null,"windgust":37.4,"windspeed":29.9,"winddir":46.7,"pressure":1013,"visibility":24.1,"cloudcover":4.4,"solarradiation":0,"solarenergy":0,"uvindex":0,"severerisk":10,"conditions":"Clear","icon":"clear-night","stations":["remote"],"source":"obs"},{"datetime":"03:00:00","datetimeEpoch":1773169200,"temp":24.6,"feelslike":24.6,"humidity":73.27,"dew":19.5,"precip":0,"precipprob":0,"snow":0,"snowdepth":null,"preciptype":["rain"],"windgust":37.1,"windspeed":29.5,"winddir":43.8,"pressure":1013,"visibility":24.1,"cloudcover":55.4,"solarradiation":0,"solarenergy":0,"uvindex":0,"severerisk":10,"conditions":"Partially cloudy","icon":"partly-cloudy-night","stations":["remote"],"source":"obs"},{"datetime":"04:00:00","datetimeEpoch":1773172800,"temp":24.5,"feelslike":24.5,"humidity":74.17,"dew":19.6,"precip":0.1,"precipprob":100,"snow":0,"snowdepth":null,"preciptype":["rain"],"windgust":35.6,"windspeed":27.7,"winddir":51.4,"pressure":1013,"visibility":24.1,"cloudcover":36.9,"solarradiation":0,"solarenergy":0,"uvindex":0,"severerisk":10,"conditions":"Rain, Partially cloudy","icon":"rain","stations":["remote"],"source":"obs"},{"datetime":"05:00:00","datetimeEpoch":1773176400,"temp":24.6,"feelslike":24.6,"humidity":72.36,"dew":19.3,"precip":0,"precipprob":0,"snow":0,"snowdepth":null,"preciptype":null,"windgust":36.4,"windspeed":28.4,"winddir":48.3,"pressure":1013,"visibility":24.1,"cloudcover":5.9,"solarradiation":0,"solarenergy":0,"uvindex":0,"severerisk":10,"conditions":"Clear","icon":"clear-night","stations":["remote"],"source":"obs"},{"datetime":"06:00:00","datetimeEpoch":1773180000,"temp":24.5,"feelslike":24.5,"humidity":73.71,"dew":19.5,"precip":0,"precipprob":0,"snow":0,"snowdepth":null,"preciptype":null,"windgust":36,"windspeed":29.2,"winddir":50.3,"pressure":1013,"visibility":24.1,"cloudcover":5,"solarradiation":0,"solarenergy":0,"uvindex":0,"severerisk":10,"conditions":"Clear","icon":"clear-night","stations":["remote"],"source":"obs"},{"datetime":"07:00:00","datetimeEpoch":1773183600,"temp":24.5,"feelslike":24.5,"humidity":73.25,"dew":19.4,"precip":0,"precipprob":0,"snow":0,"snowdepth":null,"preciptype":null,"windgust":36.4,"windspeed":29.9,"winddir":50.9,"pressure":1014,"visibility":24.1,"cloudcover":3.9,"solarradiation":62,"solarenergy":0.2,"uvindex":1,"severerisk":10,"conditions":"Clear","icon":"clear-day","stations":["remote"],"source":"obs"},{"datetime":"08:00:00","datetimeEpoch":1773187200,"temp":24.7,"feelslike":24.7,"humidity":72.38,"dew":19.4,"precip":0,"precipprob":0,"snow":null,"snowdepth":null,"preciptype":null,"windgust":34.9,"windspeed":28.8,"winddir":47.1,"pressure":1014,"visibility":24.1,"cloudcover":2.7,"solarradiation":299,"solarenergy":1.1,"uvindex":3,"severerisk":10,"conditions":"Clear","icon":"clear-day","stations":["remote"],"source":"obs"},{"datetime":"09:00:00","datetimeEpoch":1773190800,"temp":25.2,"feelslike":25.2,"humidity":69.38,"dew":19.2,"precip":0,"precipprob":0,"snow":0,"snowdepth":null,"preciptype":null,"windgust":32.4,"windspeed":27.7,"winddir":43.7,"pressure":1014,"visibility":24.1,"cloudcover":3.8,"solarradiation":546,"solarenergy":2,"uvindex":5,"severerisk":10,"conditions":"Clear","icon":"clear-day","stations":["remote"],"source":"obs"},{"datetime":"10:00:00","datetimeEpoch":1773194400,"temp":25.8,"feelslike":25.8,"humidity":66.12,"dew":19,"precip":0,"precipprob":0,"snow":0,"snowdepth":null,"preciptype":null,"windgust":29.9,"windspeed":25.6,"winddir":41.4,"pressure":1014,"visibility":24.1,"cloudcover":3.8,"solarradiation":757,"solarenergy":2.7,"uvindex":8,"severerisk":10,"conditions":"Clear","icon":"clear-day","stations":["remote"],"source":"obs"},{"datetime":"11:00:00","datetimeEpoch":1773198000,"temp":26.4,"feelslike":26.4,"humidity":63.03,"dew":18.8,"precip":0,"precipprob":0,"snow":0,"snowdepth":null,"preciptype":null,"windgust":28.8,"windspeed":24.1,"winddir":27,"pressure":1013,"visibility":24.1,"cloudcover":5.1,"solarradiation":912,"solarenergy":3.3,"uvindex":9,"severerisk":10,"conditions":"Clear","icon":"clear-day","stations":["remote"],"source":"obs"},{"datetime":"12:00:00","datetimeEpoch":1773201600,"temp":26.6,"feelslike":26.6,"humidity":64.26,"dew":19.3,"precip":0,"precipprob":0,"snow":0,"snowdepth":null,"preciptype":null,"windgust":28.8,"windspeed":27.4,"winddir":13.5,"pressure":1012,"visibility":24.1,"cloudcover":5.8,"solarradiation":997,"solarenergy":3.6,"uvindex":10,"severerisk":10,"conditions":"Clear","icon":"clear-day","stations":["remote"],"source":"obs"},{"datetime":"13:00:00","datetimeEpoch":1773205200,"temp":26.6,"feelslike":26.6,"humidity":65.47,"dew":19.6,"precip":0,"precipprob":0,"snow":0,"snowdepth":null,"preciptype":null,"windgust":30.2,"windspeed":31,"winddir":10.5,"pressure":1012,"visibility":24.1,"cloudcover":4,"solarradiation":1003,"solarenergy":3.6,"uvindex":10,"severerisk":10,"conditions":"Clear","icon":"clear-day","stations":["remote"],"source":"obs"},{"datetime":"14:00:00","datetimeEpoch":1773208800,"temp":26.5,"feelslike":26.5,"humidity":67.93,"dew":20.1,"precip":0,"precipprob":0,"snow":null,"snowdepth":null,"preciptype":null,"windgust":33.8,"windspeed":34.6,"winddir":13.5,"pressure":1011,"visibility":24.1,"cloudcover":0.8,"solarradiation":928,"solarenergy":3.3,"uvindex":9,"severerisk":10,"conditions":"Clear","icon":"clear-day","stations":["remote"],"source":"obs"},{"datetime":"15:00:00","datetimeEpoch":1773212400,"temp":26.4,"feelslike":26.4,"humidity":68.76,"dew":20.2,"precip":0,"precipprob":0,"snow":0,"snowdepth":null,"preciptype":null,"windgust":34.6,"windspeed":35.6,"winddir":13.5,"pressure":1010,"visibility":24.1,"cloudcover":4.2,"solarradiation":781,"solarenergy":2.8,"uvindex":8,"severerisk":10,"conditions":"Clear","icon":"clear-day","stations":["remote"],"source":"obs"},{"datetime":"16:00:00","datetimeEpoch":1773216000,"temp":26.4,"feelslike":26.4,"humidity":69.18,"dew":20.3,"precip":0,"precipprob":0,"snow":0,"snowdepth":null,"preciptype":null,"windgust":36,"windspeed":36,"winddir":16.9,"pressure":1010,"visibility":24.1,"cloudcover":0.1,"solarradiation":574,"solarenergy":2.1,"uvindex":6,"severerisk":10,"conditions":"Clear","icon":"clear-day","stations":["remote"],"source":"obs"},{"datetime":"17:00:00","datetimeEpoch":1773219600,"temp":26.2,"feelslike":26.2,"humidity":67.87,"dew":19.8,"precip":0,"precipprob":0,"snow":0,"snowdepth":null,"preciptype":null,"windgust":38.9,"windspeed":37.1,"winddir":20,"pressure":1010,"visibility":24.1,"cloudcover":82.2,"solarradiation":329,"solarenergy":1.2,"uvindex":3,"severerisk":10,"conditions":"Partially cloudy","icon":"partly-cloudy-day","stations":["remote"],"source":"obs"},{"datetime":"18:00:00","datetimeEpoch":1773223200,"temp":26,"feelslike":26,"humidity":67.41,"dew":19.5,"precip":0,"precipprob":0,"snow":0,"snowdepth":null,"preciptype":null,"windgust":40.7,"windspeed":38.5,"winddir":25.5,"pressure":1011,"visibility":24.1,"cloudcover":99.4,"solarradiation":78,"solarenergy":0.3,"uvindex":1,"severerisk":10,"conditions":"Overcast","icon":"cloudy","stations":["remote"],"source":"obs"},{"datetime":"19:00:00","datetimeEpoch":1773226800,"temp":26,"feelslike":26,"humidity":66.99,"dew":19.4,"precip":0,"precipprob":0,"snow":0,"snowdepth":null,"preciptype":null,"windgust":37.1,"windspeed":37.1,"winddir":37.1,"pressure":1011,"visibility":24.1,"cloudcover":1.3,"solarradiation":0,"solarenergy":0,"uvindex":0,"severerisk":10,"conditions":"Clear","icon":"clear-night","stations":["remote"],"source":"obs"},{"datetime":"20:00:00","datetimeEpoch":1773230400,"temp":25.5,"feelslike":25.5,"humidity":68.16,"dew":19.2,"precip":0,"precipprob":0,"snow":null,"snowdepth":null,"preciptype":null,"windgust":35.6,"windspeed":33.5,"winddir":45.1,"pressure":1012,"visibility":24.1,"cloudcover":5.2,"solarradiation":0,"solarenergy":0,"uvindex":0,"severerisk":10,"conditions":"Clear","icon":"clear-night","stations":null,"source":"fcst"},{"datetime":"21:00:00","datetimeEpoch":1773234000,"temp":25.2,"feelslike":25.2,"humidity":70.69,"dew":19.5,"precip":0,"precipprob":0,"snow":0,"snowdepth":null,"preciptype":null,"windgust":36,"windspeed":31.3,"winddir":49.4,"pressure":1013,"visibility":24.1,"cloudcover":99.8,"solarradiation":0,"solarenergy":0,"uvindex":0,"severerisk":10,"conditions":"Overcast","icon":"cloudy","stations":null,"source":"fcst"},{"datetime":"22:00:00","datetimeEpoch":1773237600,"temp":25,"feelslike":25,"humidity":71.1,"dew":19.4,"precip":0,"precipprob":0,"snow":0,"snowdepth":null,"preciptype":null,"windgust":36.4,"windspeed":29.9,"winddir":49.9,"pressure":1013,"visibility":24.1,"cloudcover":100,"solarradiation":0,"solarenergy":0,"uvindex":0,"severerisk":10,"conditions":"Overcast","icon":"cloudy","stations":null,"source":"fcst"},{"datetime":"23:00:00","datetimeEpoch":1773241200,"temp":24.8,"feelslike":24.8,"humidity":73.3,"dew":19.7,"precip":0,"precipprob":0,"snow":0,"snowdepth":null,"preciptype":null,"windgust":36,"windspeed":28.4,"winddir":53,"pressure":1013,"visibility":24.1,"cloudcover":100,"solarradiation":0,"solarenergy":0,"uvindex":0,"severerisk":10,"conditions":"Overcast","icon":"cloudy","stations":null,"source":"fcst"}]}],"alerts":[],"stations":{"E9058":{"distance":54277,"latitude":13.672,"longitude":121.401,"useCount":0,"id":"E9058","name":"EW9058 Laiya PH","quality":0,"contribution":0}},"currentConditions":{"datetime":"17:00:00","datetimeEpoch":1773219600,"temp":27.3,"feelslike":27.8,"humidity":52,"dew":16.6,"precip":null,"precipprob":0,"snow":null,"snowdepth":0,"preciptype":null,"windgust":11.2,"windspeed":11.2,"winddir":336,"pressure":1012,"visibility":null,"cloudcover":5.2,"solarradiation":0,"solarenergy":0,"uvindex":0,"conditions":"Clear","icon":"clear-day","stations":["E9058"],"source":"obs","sunrise":"06:02:56","sunriseEpoch":1773180176,"sunset":"18:02:40","sunsetEpoch":1773223360,"moonphase":0.75}}